README.rst
episoderenamer.py
setup.py
episode_renamer.egg-info/PKG-INFO
episode_renamer.egg-info/SOURCES.txt
episode_renamer.egg-info/dependency_links.txt
episode_renamer.egg-info/entry_points.txt
episode_renamer.egg-info/top_level.txt