Metadata-Version: 1.1
Name: episode-renamer
Version: 0.4.6
Summary: TV episode renamer
Home-page: UNKNOWN
Author: Stavros Korokithakis
Author-email: stavros@korokithakis.net
License: UNKNOWN
Platform: UNKNOWN
Classifier: License :: OSI Approved :: BSD License
Classifier: Programming Language :: Python
Classifier: Topic :: Multimedia :: Video
